odoo/addons/scrap_location_filter/README.rst
odoo/addons/scrap_location_filter/__init__.py
odoo/addons/scrap_location_filter/__manifest__.py
odoo/addons/scrap_location_filter/i18n/it.po
odoo/addons/scrap_location_filter/i18n/scrap_location_filter.pot
odoo/addons/scrap_location_filter/models/__init__.py
odoo/addons/scrap_location_filter/models/stock_location.py
odoo/addons/scrap_location_filter/models/stock_scrap.py
odoo/addons/scrap_location_filter/readme/CONTRIBUTORS.rst
odoo/addons/scrap_location_filter/readme/CREDITS.rst
odoo/addons/scrap_location_filter/readme/DESCRIPTION.rst
odoo/addons/scrap_location_filter/readme/USAGE.rst
odoo/addons/scrap_location_filter/static/description/icon.png
odoo/addons/scrap_location_filter/static/description/index.html
odoo/addons/scrap_location_filter/tests/__init__.py
odoo/addons/scrap_location_filter/tests/test_scrap_location_filter.py
odoo/addons/scrap_location_filter/views/stock_views.xml
odoo14_addon_scrap_location_filter-14.0.1.0.1.dev5.dist-info/METADATA
odoo14_addon_scrap_location_filter-14.0.1.0.1.dev5.dist-info/WHEEL
odoo14_addon_scrap_location_filter-14.0.1.0.1.dev5.dist-info/top_level.txt
odoo14_addon_scrap_location_filter-14.0.1.0.1.dev5.dist-info/RECORD
